{
  "common/footer.css": "common/footer-0756841ec8.css",
  "common/header.css": "common/header-7c79e25c3c.css",
  "common/index.css": "common/index-6554050008.css",
  "common/menu.css": "common/menu-571df80a20.css",
  "common/promo.css": "common/promo-d41d8cd98f.css",
  "common/search.css": "common/search-e29fe8a0a1.css",
  "detail/index.css": "detail/index-e796dd2305.css",
  "home/index.css": "home/index-ae4ca8d99b.css",
  "home/promo.css": "home/promo-d41d8cd98f.css",
  "list/index.css": "list/index-8ea070632a.css",
  "publish/index.css": "publish/index-818d63a84d.css",
  "shopping/buy.css": "shopping/buy-907176ff76.css"
}